setup.py
vesselPackage/__init__.py
vesselPackage/encryption.py
vesselPackage/generate_random_string.py
vesselPackage/getpagination.py
vesselPackage/otp.py
vesselPackage/pagination.py
vesselPackage/uniqueID.py
vesselPackage.egg-info/PKG-INFO
vesselPackage.egg-info/SOURCES.txt
vesselPackage.egg-info/dependency_links.txt
vesselPackage.egg-info/top_level.txt